quinductor/__init__.py
quinductor/common.py
quinductor/core.py
quinductor/guards.py
quinductor/lang_spec_feats.json
quinductor/loaders.py
quinductor/make_templates.py
quinductor/repro.py
quinductor/rules.py
quinductor-0.2.2.dist-info/LICENSE
quinductor-0.2.2.dist-info/METADATA
quinductor-0.2.2.dist-info/WHEEL
quinductor-0.2.2.dist-info/top_level.txt
quinductor-0.2.2.dist-info/RECORD
